nimbalwear/__init__.py
nimbalwear/__version__.py
nimbalwear/activity.py
nimbalwear/data.py
nimbalwear/gait.py
nimbalwear/gait_accel.py
nimbalwear/gait_gyro.py
nimbalwear/nonwear.py
nimbalwear/pipeline.py
nimbalwear/sleep.py
nimbalwear/data/pushoff_df.csv
nimbalwear/files/CWA.py
nimbalwear/files/EDF.py
nimbalwear/files/GENEActiv.py
nimbalwear/files/Sibel.py
nimbalwear/files/__init__.py
nimbalwear/reports/__init__.py
nimbalwear/reports/collection_report.py
nimbalwear/settings/settings.toml
nimbalwear/utils/__init__.py
nimbalwear/utils/autocal.py
nimbalwear/utils/file.py
nimbalwear/utils/misc.py
nimbalwear/utils/sync.py
nimbalwear-0.21.8.dist-info/LICENSE
nimbalwear-0.21.8.dist-info/METADATA
nimbalwear-0.21.8.dist-info/WHEEL
nimbalwear-0.21.8.dist-info/top_level.txt
nimbalwear-0.21.8.dist-info/RECORD
