Metadata-Version: 2.1
Name: nimbalwear
Version: 0.21.8
Summary: NiMBaLWear wearable device data processing pipeline.
Home-page: https://github.com/nimbal/nimbalwear
Author: Kit Beyer
Author-email: kitbeyer@gmail.com
Classifier: Programming Language :: Python :: 3
Classifier: License :: OSI Approved :: MIT License
Classifier: Operating System :: OS Independent
Requires-Python: >=3.9
License-File: LICENSE
Requires-Dist: numpy <2.0.0,>=1.22.4
Requires-Dist: numba >=0.59.0
Requires-Dist: pandas >=1.4.0
Requires-Dist: matplotlib <3.9,>=3.5.2
Requires-Dist: tqdm >=4.64.0
Requires-Dist: isodate >=0.6.1
Requires-Dist: scipy >=1.7.3
Requires-Dist: pyedflib >=0.1.34
Requires-Dist: flatten-dict >=0.4.2
Requires-Dist: scikit-learn >=1.1.1
Requires-Dist: fpdf >=1.7.2
Requires-Dist: toml >=0.10.2
Requires-Dist: msoffcrypto-tool >=5.0.0
Requires-Dist: nimbaldetach >=1.0.3
Requires-Dist: openpyxl
